chaosaws/__init__.py
chaosaws/asg/__init__.py
chaosaws/asg/actions.py
chaosaws/asg/probes.py
chaosaws/awslambda/__init__.py
chaosaws/awslambda/actions.py
chaosaws/awslambda/probes.py
chaosaws/cloudwatch/__init__.py
chaosaws/cloudwatch/actions.py
chaosaws/cloudwatch/probes.py
chaosaws/ec2/__init__.py
chaosaws/ec2/actions.py
chaosaws/ec2/probes.py
chaosaws/ecs/__init__.py
chaosaws/ecs/actions.py
chaosaws/ecs/probes.py
chaosaws/eks/__init__.py
chaosaws/eks/actions.py
chaosaws/eks/probes.py
chaosaws/elasticache/__init__.py
chaosaws/elasticache/actions.py
chaosaws/elasticache/probes.py
chaosaws/elbv2/__init__.py
chaosaws/elbv2/actions.py
chaosaws/elbv2/probes.py
chaosaws/emr/__init__.py
chaosaws/emr/actions.py
chaosaws/emr/probes.py
chaosaws/emr/shared.py
chaosaws/fis/__init__.py
chaosaws/fis/actions.py
chaosaws/fis/probes.py
chaosaws/iam/__init__.py
chaosaws/iam/actions.py
chaosaws/iam/probes.py
chaosaws/incidents/__init__.py
chaosaws/incidents/probes.py
chaosaws/msk/__init__.py
chaosaws/msk/actions.py
chaosaws/msk/probes.py
chaosaws/rds/__init__.py
chaosaws/rds/actions.py
chaosaws/rds/probes.py
chaosaws/route53/__init__.py
chaosaws/route53/actions.py
chaosaws/route53/probes.py
chaosaws/route53/shared.py
chaosaws/s3/__init__.py
chaosaws/s3/actions.py
chaosaws/s3/controls/__init__.py
chaosaws/s3/controls/upload.py
chaosaws/s3/probes.py
chaosaws/s3/shared.py
chaosaws/ssm/__init__.py
chaosaws/ssm/actions.py
chaosaws/ssm/probes.py
chaosaws/types.py
chaosaws/utils.py
chaosaws/xray/__init__.py
chaosaws/xray/probes.py
chaostoolkit_aws-0.34.0.dist-info/METADATA
chaostoolkit_aws-0.34.0.dist-info/WHEEL
chaostoolkit_aws-0.34.0.dist-info/licenses/LICENSE
chaostoolkit_aws-0.34.0.dist-info/RECORD
