Metadata-Version: 2.1
Name: chaostoolkit-aws
Version: 0.34.0
Summary: AWS extension for the Chaos Toolkit
Author-Email: Chaos Toolkit <contact@chaostoolkit.org>, Sylvain Hellegouarch <sh@defuze.org>
License: Apache-2.0
Classifier: Development Status :: 5 - Production/Stable
Classifier: Intended Audience :: Developers
Classifier: License :: Freely Distributable
Classifier: License :: OSI Approved :: Apache Software License
Classifier: Operating System :: OS Independent
Classifier: Programming Language :: Python
Classifier: Programming Language :: Python :: 3
Classifier: Programming Language :: Python :: 3.8
Classifier: Programming Language :: Python :: 3.9
Classifier: Programming Language :: Python :: 3.10
Classifier: Programming Language :: Python :: 3.11
Classifier: Programming Language :: Python :: 3.12
Classifier: Programming Language :: Python :: Implementation
Classifier: Programming Language :: Python :: Implementation :: CPython
Project-URL: Homepage, https://chaostoolkit.org/
Project-URL: Repository, https://github.com/chaostoolkit-incubator/chaostoolkit-aws
Project-URL: Documentation, https://chaostoolkit.org/drivers/aws/
Project-URL: Changelog, https://github.com/chaostoolkit-incubator/chaostoolkit-aws/blob/main/CHANGELOG.md
Requires-Python: >=3.8
Requires-Dist: aws-requests-auth>=0.4.3
Requires-Dist: boto3>=1.34.48
Requires-Dist: requests>=2.31.0
Requires-Dist: chaostoolkit-lib>=1.42.0
